scoreboard_ooo/scoreboard_ooo.srcs/sources_1/new/writeback_unit.v
module writeback_unit(
    input clk,
    input reset,
    input fu_done,
    input [4:0] rd_exec,
    output reg wb_en,
    output reg [4:0] rd_wb
);

always @(posedge clk or posedge reset) begin
    if (reset) begin
        wb_en <= 0;
        rd_wb <= 0;
    end
    else begin
        if (fu_done) begin
            wb_en <= 1;
            rd_wb <= rd_exec;
        end
        else begin
            wb_en <= 0;
        end
    end
end

endmodule

scoreboard_ooo/scoreboard_ooo.srcs/sources_1/new/functional_unit.v
module functional_unit(
    input clk,
    input reset,
    input start,
    input [3:0] opcode,
    output reg done
);

reg [2:0] counter;
reg [2:0] latency;

always @(*) begin
    case(opcode)
        4'b0001: latency = 1;
        4'b0011: latency = 3;
        4'b0100: latency = 5;
        default: latency = 1;
    endcase
end

always @(posedge clk or posedge reset) begin
    if (reset) begin
        counter <= 0;
        done <= 0;
    end else if (start) begin
        counter <= latency;
        done <= 0;
    end else if (counter > 0) begin
        counter <= counter - 1;
        if (counter == 1)
            done <= 1;
    end else
        done <= 0;
end

endmodule

scoreboard_ooo/scoreboard_ooo.srcs/sources_1/new/issue_logic.v
module issue_logic(
    input [31:0] busy_table,
    input [4:0] rs1,
    input [4:0] rs2,
    input [4:0] rd,
    output can_issue
);

assign can_issue =
       ~busy_table[rs1] &&
       ~busy_table[rs2] &&
       ~busy_table[rd];

endmodule

scoreboard_ooo/scoreboard_ooo.srcs/sources_1/new/scoreboard_table.v
`timescale 1ns / 1ps
//////////////////////////////////////////////////////////////////////////////////
// Company: 
// Engineer: 
// 
// Create Date: 03/01/2026 05:31:28 PM
// Design Name: 
// Module Name: scoreboard_table
// Project Name: 
// Target Devices: 
// Tool Versions: 
// Description: 
// 
// Dependencies: 
// 
// Revision:
// Revision 0.01 - File Created
// Additional Comments:
// 
//////////////////////////////////////////////////////////////////////////////////


module scoreboard_table(
    input clk,
    input reset,
    input issue,
    input writeback,
    input [4:0] rd_issue,
    input [4:0] rd_wb,
    output [31:0] busy_table
);

reg [31:0] busy;

assign busy_table = busy;

always @(posedge clk or posedge reset) begin
    if (reset)
        busy <= 0;
    else begin
        if (issue)
            busy[rd_issue] <= 1;
        if (writeback)
            busy[rd_wb] <= 0;
    end
end

endmodule

scoreboard_ooo/scoreboard_ooo.srcs/sources_1/new/scoreboard_top.v
module scoreboard_top(
    input clk,
    input reset
);

// ----------------------
// Instruction Register
// ----------------------
reg [31:0] instr_reg;

// Example instruction stream (manual feed)
always @(posedge clk or posedge reset) begin
    if (reset)
        instr_reg <= 32'h10088000;  // dummy ADD
    else
        instr_reg <= instr_reg;     // static for now
end

// ----------------------
// Decode fields
// ----------------------
wire [3:0] opcode = instr_reg[31:28];
wire [4:0] rd     = instr_reg[27:23];
wire [4:0] rs1    = instr_reg[22:18];
wire [4:0] rs2    = instr_reg[17:13];

// ----------------------
// Scoreboard
// ----------------------
wire [31:0] busy_table;
wire wb_en;
wire [4:0] rd_wb;

scoreboard_table sb(
    .clk(clk),
    .reset(reset),
    .issue(issue_en),
    .writeback(wb_en),
    .rd_issue(rd),
    .rd_wb(rd_wb),
    .busy_table(busy_table)
);

// ----------------------
// Issue Logic
// ----------------------
wire can_issue;
reg issue_en;

issue_logic issue_unit(
    .busy_table(busy_table),
    .rs1(rs1),
    .rs2(rs2),
    .rd(rd),
    .can_issue(can_issue)
);

// ----------------------
// Reservation Station
// ----------------------
reg rs_busy;

always @(posedge clk or posedge reset) begin
    if (reset)
        rs_busy <= 0;
    else if (issue_en)
        rs_busy <= 1;
    else if (wb_en)
        rs_busy <= 0;
end

// ----------------------
// Functional Unit
// ----------------------
wire fu_done;
reg fu_start;

functional_unit fu(
    .clk(clk),
    .reset(reset),
    .start(fu_start),
    .opcode(opcode),
    .done(fu_done)
);

// ----------------------
// Writeback
// ----------------------
writeback_unit wb(
    .clk(clk),
    .reset(reset),
    .fu_done(fu_done),
    .rd_exec(rd),
    .wb_en(wb_en),
    .rd_wb(rd_wb)
);

// ----------------------
// Control FSM
// ----------------------
reg [1:0] state;

localparam FETCH     = 2'd0,
           ISSUE     = 2'd1,
           EXECUTE   = 2'd2,
           WRITEBACK = 2'd3;

always @(posedge clk or posedge reset) begin
    if (reset) begin
        state <= FETCH;
        issue_en <= 0;
        fu_start <= 0;
    end
    else begin
        case(state)

        FETCH: begin
            issue_en <= 0;
            fu_start <= 0;
            state <= ISSUE;
        end

        ISSUE: begin
            if (can_issue && !rs_busy) begin
                issue_en <= 1;
                state <= EXECUTE;
            end
            else begin
                issue_en <= 0;
            end
        end

        EXECUTE: begin
            issue_en <= 0;
            fu_start <= 1;
            state <= WRITEBACK;
        end

        WRITEBACK: begin
            fu_start <= 0;
            if (fu_done)
                state <= FETCH;
        end

        endcase
    end
end

endmodule

scoreboard_ooo/scoreboard_ooo.srcs/sim_1/new/tb_scoreboard.v
`timescale 1ns / 1ps
//////////////////////////////////////////////////////////////////////////////////
// Company: 
// Engineer: 
// 
// Create Date: 03/01/2026 05:35:23 PM
// Design Name: 
// Module Name: tb_scoreboard
// Project Name: 
// Target Devices: 
// Tool Versions: 
// Description: 
// 
// Dependencies: 
// 
// Revision:
// Revision 0.01 - File Created
// Additional Comments:
// 
//////////////////////////////////////////////////////////////////////////////////

module tb_scoreboard;

reg clk = 0;
reg reset = 1;

always #5 clk = ~clk;

scoreboard_top DUT(
    .clk(clk),
    .reset(reset)
);

initial begin
    $dumpfile("wave.vcd");
    $dumpvars(0, DUT);

    #20 reset = 0;
    #500 $finish;
end

endmodule

scoreboard_ooo/scoreboard_ooo.sim/sim_1/behav/xsim/wave.vcd
$date
   Sun Mar  1 17:38:31 2026
$end

$version
  2023.2
  $dumpfile ("wave.vcd") 
$end

$timescale
  1ps
$end

$scope module tb_scoreboard $end
$scope module DUT $end
$var wire 1 ! clk $end
$var wire 1 " reset $end
$var reg 32 # instr_reg [31:0] $end
$var wire 4 $ opcode [3:0] $end
$var wire 5 % rd [4:0] $end
$var wire 5 & rs1 [4:0] $end
$var wire 5 ' rs2 [4:0] $end
$var wire 32 ( busy_table [31:0] $end
$var wire 1 ) wb_en $end
$var wire 5 * rd_wb [4:0] $end
$var wire 1 + can_issue $end
$var reg 1 , issue_en $end
$var reg 1 - rs_busy $end
$var wire 1 . fu_done $end
$var reg 1 / fu_start $end
$var reg 2 0 state [1:0] $end
$scope module sb $end
$var wire 1 ! clk $end
$var wire 1 " reset $end
$var wire 1 1 issue $end
$var wire 1 ) writeback $end
$var wire 5 % rd_issue [4:0] $end
$var wire 5 * rd_wb [4:0] $end
$var wire 32 ( busy_table [31:0] $end
$var reg 32 2 busy [31:0] $end
$upscope $end
$scope module issue_unit $end
$var wire 32 ( busy_table [31:0] $end
$var wire 5 & rs1 [4:0] $end
$var wire 5 ' rs2 [4:0] $end
$var wire 5 % rd [4:0] $end
$var wire 1 + can_issue $end
$upscope $end
$scope module fu $end
$var wire 1 ! clk $end
$var wire 1 " reset $end
$var wire 1 3 start $end
$var wire 4 $ opcode [3:0] $end
$var reg 1 4 done $end
$var reg 3 5 counter [2:0] $end
$var reg 3 6 latency [2:0] $end
$upscope $end
$scope module wb $end
$var wire 1 ! clk $end
$var wire 1 " reset $end
$var wire 1 . fu_done $end
$var wire 5 % rd_exec [4:0] $end
$var reg 1 7 wb_en $end
$var reg 5 8 rd_wb [4:0] $end
$upscope $end
$upscope $end
$upscope $end
$enddefinitions $end

#0
$dumpvars
0!
1"
b10000000010001000000000000000 #
b1 $
b0 %
b10 &
b100 '
b0 (
0)
b0 *
1+
0,
0-
0.
0/
b0 0
01
b0 2
03
04
b0 5
b1 6
07
b0 8
$end

#5000
1!

#10000
0!

#15000
1!

#20000
0!
0"

#25000
1!
b1 0

#30000
0!

#35000
1!
1,
b10 0
11

#40000
0!

#45000
1!
b1 (
0+
0,
1-
1/
b11 0
01
b1 2
13

#50000
0!

#55000
1!
0/
03
b1 5

#60000
0!

#65000
1!
1.
14
b0 5

#70000
0!

#75000
1!
1)
0.
b0 0
04
17

#80000
0!

#85000
1!
b0 (
0)
1+
0-
b1 0
b0 2
07

#90000
0!

#95000
1!
1,
b10 0
11

#100000
0!

#105000
1!
b1 (
0+
0,
1-
1/
b11 0
01
b1 2
13

#110000
0!

#115000
1!
0/
03
b1 5

#120000
0!

#125000
1!
1.
14
b0 5

#130000
0!

#135000
1!
1)
0.
b0 0
04
17

#140000
0!

#145000
1!
b0 (
0)
1+
0-
b1 0
b0 2
07

#150000
0!

#155000
1!
1,
b10 0
11

#160000
0!

#165000
1!
b1 (
0+
0,
1-
1/
b11 0
01
b1 2
13

#170000
0!

#175000
1!
0/
03
b1 5

#180000
0!

#185000
1!
1.
14
b0 5

#190000
0!

#195000
1!
1)
0.
b0 0
04
17

#200000
0!

#205000
1!
b0 (
0)
1+
0-
b1 0
b0 2
07

#210000
0!

#215000
1!
1,
b10 0
11

#220000
0!

#225000
1!
b1 (
0+
0,
1-
1/
b11 0
01
b1 2
13

#230000
0!

#235000
1!
0/
03
b1 5

#240000
0!

#245000
1!
1.
14
b0 5

#250000
0!

#255000
1!
1)
0.
b0 0
04
17

#260000
0!

#265000
1!
b0 (
0)
1+
0-
b1 0
b0 2
07

#270000
0!

#275000
1!
1,
b10 0
11

#280000
0!

#285000
1!
b1 (
0+
0,
1-
1/
b11 0
01
b1 2
13

#290000
0!

#295000
1!
0/
03
b1 5

#300000
0!

#305000
1!
1.
14
b0 5

#310000
0!

#315000
1!
1)
0.
b0 0
04
17

#320000
0!

#325000
1!
b0 (
0)
1+
0-
b1 0
b0 2
07

#330000
0!

#335000
1!
1,
b10 0
11

#340000
0!

#345000
1!
b1 (
0+
0,
1-
1/
b11 0
01
b1 2
13

#350000
0!

#355000
1!
0/
03
b1 5

#360000
0!

#365000
1!
1.
14
b0 5

#370000
0!

#375000
1!
1)
0.
b0 0
04
17

#380000
0!

#385000
1!
b0 (
0)
1+
0-
b1 0
b0 2
07

#390000
0!

#395000
1!
1,
b10 0
11

#400000
0!

#405000
1!
b1 (
0+
0,
1-
1/
b11 0
01
b1 2
13

#410000
0!

#415000
1!
0/
03
b1 5

#420000
0!

#425000
1!
1.
14
b0 5

#430000
0!

#435000
1!
1)
0.
b0 0
04
17

#440000
0!

#445000
1!
b0 (
0)
1+
0-
b1 0
b0 2
07

#450000
0!

#455000
1!
1,
b10 0
11

#460000
0!

#465000
1!
b1 (
0+
0,
1-
1/
b11 0
01
b1 2
13

#470000
0!

#475000
1!
0/
03
b1 5

#480000
0!

#485000
1!
1.
14
b0 5

#490000
0!

#495000
1!
1)
0.
b0 0
04
17

#500000
0!

#505000
1!
b0 (
0)
1+
0-
b1 0
b0 2
07

#510000
0!

#515000
1!
1,
b10 0
11
